perceiver_ar_pytorch/__init__.py
perceiver_ar_pytorch/autoregressive_wrapper.py
perceiver_ar_pytorch/perceiver_ar_pytorch.py
perceiver_ar_pytorch-0.0.10.dist-info/LICENSE
perceiver_ar_pytorch-0.0.10.dist-info/METADATA
perceiver_ar_pytorch-0.0.10.dist-info/WHEEL
perceiver_ar_pytorch-0.0.10.dist-info/top_level.txt
perceiver_ar_pytorch-0.0.10.dist-info/RECORD
